{
  "name": "GuiToLuaConverter",
  "tree": {
    "$className": "DataModel",

    "ServerStorage": {
      "Plugin": {
        "$path": "PluginPlace/src/"
      }
    },

    "Workspace": {
      "$properties": {
        "FilteringEnabled": true
      }
    },
    "Lighting": {
      "$properties": {
        "Ambient": [
          0,
          0,
          0
        ],
        "Brightness": 2,
        "GlobalShadows": true,
        "Outlines": false,
        "Technology": "Voxel"
      }
    },
    "SoundService": {
      "$properties": {
        "RespectFilteringEnabled": true
      }
    }
  }
}